{
  "$schema": "https://developer.microsoft.com/json-schemas/spfx-build/spfx-serve.schema.json",
  "port": 4321,
  "https": true,
  "serveConfigurations": {
    "default": {
      "pageUrl": "https://{tenantDomain}/SitePages/myPage.aspx",
      "customActions": {
        "959e2f3d-d5c4-4c72-baaa-86a486df9333": {
          "location": "ClientSideExtension.ApplicationCustomizer",
          "properties": {
            "testMessage": "Test message"
          }
        }
      }
    },
    "commonStyleExt": {
      "pageUrl": "https://{tenantDomain}/SitePages/myPage.aspx",
      "customActions": {
        "959e2f3d-d5c4-4c72-baaa-86a486df9333": {
          "location": "ClientSideExtension.ApplicationCustomizer",
          "properties": {
            "testMessage": "Test message"
          }
        }
      }
    }
  }
}
